pycounts_jl/__init__.py
pycounts_jl/data/__init__.py
pycounts_jl/data/flatland.txt
pycounts_jl/datasets.py
pycounts_jl/plotting.py
pycounts_jl/pycounts_jl.py
pycounts_jl-0.4.0.dist-info/LICENSE
pycounts_jl-0.4.0.dist-info/WHEEL
pycounts_jl-0.4.0.dist-info/METADATA
pycounts_jl-0.4.0.dist-info/RECORD
